ovos_config_assistant/__init__.py
ovos_config_assistant/__main__.py
ovos_config_assistant/app.py
ovos_config_assistant/backend.py
ovos_config_assistant/datasets.py
ovos_config_assistant/menu.py
ovos_config_assistant/oauth.py
ovos_config_assistant/pairing.py
ovos_config_assistant/plugins.py
ovos_config_assistant/version.py
ovos_config_assistant/res/OCA.png
ovos_config_assistant/res/backend_settings.png
ovos_config_assistant/res/devices.png
ovos_config_assistant/res/metrics.png
ovos_config_assistant/res/microservices_config.png
ovos_config_assistant/res/oauth.png
ovos_config_assistant/res/open_dataset.png
ovos_config_assistant/res/plugins_manager.png
ovos_config_assistant/res/selene_proxy.png
ovos_config_assistant/res/utterances.png
ovos_config_assistant/res/wakewords.png
ovos_config_assistant-0.0.0a10.dist-info/LICENSE
ovos_config_assistant-0.0.0a10.dist-info/METADATA
ovos_config_assistant-0.0.0a10.dist-info/WHEEL
ovos_config_assistant-0.0.0a10.dist-info/top_level.txt
ovos_config_assistant-0.0.0a10.dist-info/RECORD
